README.md
setup.py
Appium_Python_Client_Monkey.egg-info/PKG-INFO
Appium_Python_Client_Monkey.egg-info/SOURCES.txt
Appium_Python_Client_Monkey.egg-info/dependency_links.txt
Appium_Python_Client_Monkey.egg-info/requires.txt
Appium_Python_Client_Monkey.egg-info/top_level.txt
appium_patch/__init__.py
appium_patch/monkey.py
appium_patch/version.py