Metadata-Version: 2.1
Name: Appium-Python-Client-Monkey
Version: 1.0.0
Summary: Hot Patch For Appium-Pyhton-Client
Home-page: https://github.com/CN-Robert-LIU/appium-python-client-monkey
Author: CN-Robert-LIU
Author-email: liujhon2019@163.com
License: Apache 2.0
Platform: all
Classifier: Development Status :: 4 - Beta
Classifier: Operating System :: OS Independent
Classifier: Intended Audience :: Developers
Classifier: License :: OSI Approved :: BSD License
Classifier: Programming Language :: Python :: Implementation
Classifier: Programming Language :: Python
Classifier: Programming Language :: Python :: 3.7
Classifier: Programming Language :: Python :: 3.8
Classifier: Programming Language :: Python :: 3.9
Classifier: Topic :: Software Development :: Libraries
